{"data":{"body":{"revenue":[{"name":"PHONE","value":1382,"change":1182,"code":"phone"},{"name":"WEB","value":285,"change":-4154,"code":"web"}],"roomsSold":[{"name":"PHONE","value":1,"change":1,"code":"phone"},{"name":"WEB","value":1,"change":-20,"code":"web"}],"adr":[{"name":"PHONE","value":1382,"change":1382,"code":"phone"},{"name":"WEB","value":285,"change":74,"code":"web"}],"timeSeriesData":[{"date":"2025-03","categories":{"web":{"current":285,"previous":3707},"phone":{"current":1382,"previous":200}}},{"date":"2025-04","categories":{"web":{"current":0,"previous":732},"phone":{"current":0,"previous":0}}},{"date":"2025-05","categories":{"web":{"current":0,"previous":0},"phone":{"current":0,"previous":0}}}]},"status":200,"headers":{"Content-Type":"application/json"}},"expiresAt":1743458740011}